pictriever/__init__.py
pictriever/image_scraper.py
pictriever-0.1.1.dist-info/METADATA
pictriever-0.1.1.dist-info/WHEEL
pictriever-0.1.1.dist-info/RECORD
