Metadata-Version: 2.1
Name: pictriever
Version: 0.1.1
Summary: Python library for image scraping, from popular image gallery sites.
Home-page: https://github.com/kelechi-c/pictriever
License: apache 2.0
Keywords: image,datasets,scraping
Author: tensorkelechi
Author-email: kelechichibuzo7@gmail.com
Requires-Python: >=3.6,<4.0
Classifier: License :: Other/Proprietary License
Classifier: Programming Language :: Python :: 3
Classifier: Programming Language :: Python :: 3.6
Classifier: Programming Language :: Python :: 3.7
Classifier: Programming Language :: Python :: 3.8
Classifier: Programming Language :: Python :: 3.9
Classifier: Programming Language :: Python :: 3.10
Classifier: Programming Language :: Python :: 3.11
Classifier: Programming Language :: Python :: 3.12
Requires-Dist: requests (>=2.32.3,<3.0.0)
Requires-Dist: rich (>=13.7.1,<14.0.0)
Requires-Dist: selenium (>=4.21.0,<5.0.0)
Requires-Dist: tqdm (>=4.66.4,<5.0.0)
Project-URL: Repository, https://github.com/kelechi-c/pictriever
